odoo/addons/sale_commission_formula/README.rst
odoo/addons/sale_commission_formula/__init__.py
odoo/addons/sale_commission_formula/__manifest__.py
odoo/addons/sale_commission_formula/demo/commission_demo.xml
odoo/addons/sale_commission_formula/i18n/ca.po
odoo/addons/sale_commission_formula/i18n/de.po
odoo/addons/sale_commission_formula/i18n/el_GR.po
odoo/addons/sale_commission_formula/i18n/es.po
odoo/addons/sale_commission_formula/i18n/es_AR.po
odoo/addons/sale_commission_formula/i18n/fi.po
odoo/addons/sale_commission_formula/i18n/fr.po
odoo/addons/sale_commission_formula/i18n/it.po
odoo/addons/sale_commission_formula/i18n/pt.po
odoo/addons/sale_commission_formula/i18n/pt_BR.po
odoo/addons/sale_commission_formula/i18n/pt_PT.po
odoo/addons/sale_commission_formula/i18n/ru.po
odoo/addons/sale_commission_formula/i18n/sale_commission_formula.pot
odoo/addons/sale_commission_formula/i18n/sl.po
odoo/addons/sale_commission_formula/i18n/tr.po
odoo/addons/sale_commission_formula/i18n/tr_TR.po
odoo/addons/sale_commission_formula/i18n/zh_CN.po
odoo/addons/sale_commission_formula/migrations/13.0.1.0.0/pre-migration.py
odoo/addons/sale_commission_formula/models/__init__.py
odoo/addons/sale_commission_formula/models/sale_commission.py
odoo/addons/sale_commission_formula/models/sale_commission_mixin.py
odoo/addons/sale_commission_formula/readme/CONTRIBUTORS.rst
odoo/addons/sale_commission_formula/readme/DESCRIPTION.rst
odoo/addons/sale_commission_formula/readme/USAGE.rst
odoo/addons/sale_commission_formula/static/description/icon.png
odoo/addons/sale_commission_formula/static/description/icon.svg
odoo/addons/sale_commission_formula/static/description/index.html
odoo/addons/sale_commission_formula/static/src/css/sale_commission_formula.css
odoo/addons/sale_commission_formula/tests/__init__.py
odoo/addons/sale_commission_formula/tests/test_commission_formula.py
odoo/addons/sale_commission_formula/views/sale_commission_view.xml
odoo13_addon_sale_commission_formula-13.0.1.1.1.dist-info/METADATA
odoo13_addon_sale_commission_formula-13.0.1.1.1.dist-info/WHEEL
odoo13_addon_sale_commission_formula-13.0.1.1.1.dist-info/top_level.txt
odoo13_addon_sale_commission_formula-13.0.1.1.1.dist-info/RECORD
