Metadata-Version: 2.1
Name: odoo13-addon-sale-commission-formula
Version: 13.0.1.1.1
Summary: Sale commissions computed by formulas
Home-page: https://github.com/OCA/commission
Author: Abstract,Odoo Community Association (OCA)
Author-email: support@odoo-community.org
License: AGPL-3
Platform: UNKNOWN
Classifier: Programming Language :: Python
Classifier: Framework :: Odoo
Classifier: License :: OSI Approved :: GNU Affero General Public License v3
Requires-Python: >=3.5
Requires-Dist: odoo13-addon-sale-commission
Requires-Dist: odoo (<13.1dev,>=13.0a)
